icecream/__init__.py
icecream/__version__.py
icecream/builtins.py
icecream/coloring.py
icecream/icecream.py
icecream-2.1.7.dist-info/licenses/LICENSE.txt
tests/__init__.py
tests/install_test_import.py
tests/test_icecream.py
tests/test_install.py
icecream-2.1.7.dist-info/METADATA
icecream-2.1.7.dist-info/WHEEL
icecream-2.1.7.dist-info/top_level.txt
icecream-2.1.7.dist-info/RECORD
